{
  "parent": "minecraft:recipes/root",
  "rewards": {
    "recipes": [
      "meadow:red_carpet"
    ]
  },
  "criteria": {
    "has_red_wool": {
      "trigger": "minecraft:inventory_changed",
      "conditions": {
        "items": [
          {
            "items": [
              "meadow:red_wool"
            ]
          }
        ]
      }
    },
    "has_the_recipe": {
      "trigger": "minecraft:recipe_unlocked",
      "conditions": {
        "recipe": "meadow:red_carpet"
      }
    }
  },
  "requirements": [
    [
      "has_red_wool",
      "has_the_recipe"
    ]
  ]
}